cronvice/__init__.py
cronvice/cmd_parser.py
cronvice/config.py
cronvice/df_table.py
cronvice/fn_lo.py
cronvice/fn_load.py
cronvice/fn_show.py
cronvice/interpreter.py
cronvice/key_enter.py
cronvice/libs_cron.py
cronvice/libs_screen.py
cronvice/mmapwr.py
cronvice/objects.py
cronvice/topbar.py
cronvice/version.py
cronvice-0.1.60.dev0.data/scripts/cronvice
cronvice-0.1.60.dev0.dist-info/METADATA
cronvice-0.1.60.dev0.dist-info/WHEEL
cronvice-0.1.60.dev0.dist-info/top_level.txt
cronvice-0.1.60.dev0.dist-info/RECORD
