Metadata-Version: 2.4
Name: cronvice
Version: 0.1.60.dev0
Summary: Automatically created environment for python package
Home-page: https://gitlab.com/ojr/cronvice
Author: me
Author-email: ojr@gmail.com
License: GPL2
Requires-Dist: fire
Requires-Dist: console
Requires-Dist: sshkeyboard
Requires-Dist: pytermgui
Requires-Dist: blessings
Requires-Dist: terminaltables
Requires-Dist: pandas
Requires-Dist: pyfiglet
Requires-Dist: prompt_toolkit
Requires-Dist: python-crontab
Dynamic: author
Dynamic: author-email
Dynamic: description
Dynamic: description-content-type
Dynamic: home-page
Dynamic: license
Dynamic: requires-dist
Dynamic: summary
